Fixmydata/__init__.py
Fixmydata/cleaning.py
Fixmydata/data_validator.py
Fixmydata/outlier_detector.py
Fixmydata/stats.py
Fixmydata/utils.py
fixmydata-0.1.0.dist-info/licenses/LICENSE
fixmydata-0.1.0.dist-info/METADATA
fixmydata-0.1.0.dist-info/WHEEL
fixmydata-0.1.0.dist-info/top_level.txt
fixmydata-0.1.0.dist-info/RECORD
