Metadata-Version: 2.4
Name: fixmydata
Version: 0.1.0
Summary: Fixmydata is a lightweight helper library built on top of pandas for cleaning, validating, and inspecting tabular datasets.
Home-page: https://github.com/DirtCrew53/Fixmydata
Author: Johann Lloyd Megalbio
Author-email: megalbio.johann@gmail.com
License: MIT License
Project-URL: Homepage, https://github.com/DirtCrew53/Fixmydata
Project-URL: Repository, https://github.com/DirtCrew53/Fixmydata
Keywords: data-cleaning,validation,outliers,pandas
Requires-Python: >=3.8
License-File: LICENSE
Requires-Dist: pandas<2,>=1.3
Requires-Dist: numpy<2,>=1.21
Dynamic: author-email
Dynamic: home-page
Dynamic: license-file
